r614_postgres/__init__.py
r614_postgres/postgres.py
r614_postgres/py.typed
r614_postgres/retries.py
r614_postgres/validation.py
r614_postgres-0.1.18.dist-info/LICENSE
r614_postgres-0.1.18.dist-info/METADATA
r614_postgres-0.1.18.dist-info/WHEEL
r614_postgres-0.1.18.dist-info/RECORD
