Metadata-Version: 2.1
Name: r614-postgres
Version: 0.1.18
Summary: Postgres wrapper for python
License: CC0 1.0
Author: Roshan Pawar
Author-email: steradian614@gmail.com
Requires-Python: >=3.11,<4.0
Classifier: License :: Other/Proprietary License
Classifier: Programming Language :: Python :: 3
Classifier: Programming Language :: Python :: 3.11
Requires-Dist: opentelemetry-api (>=1.15.0,<2.0.0)
Requires-Dist: opentelemetry-sdk (>=1.15.0,<2.0.0)
Requires-Dist: psycopg[binary,pool] (>=3.1.8,<4.0.0)
Requires-Dist: r614-config (>=0.1.7,<0.2.0)
Requires-Dist: r614-o11y (>=0.1.5,<0.2.0)
Requires-Dist: typing-extensions (>=4.4.0,<5.0.0)
